[
    {
        "row": [
            "ALL",
            "104年",
            "12月"
        ],
        "col": [
            "基隆市"
        ],
        "colCode": null,
        "value": 31,
        "descriptionHtml": null,
        "qty": 0,
        "diff": null,
        "tooltip": null
    },
    {
        "row": [
            "ALL",
            "104年",
            "12月"
        ],
        "col": [
            "臺北市"
        ],
        "colCode": null,
        "value": 137,
        "descriptionHtml": null,
        "qty": 0,
        "diff": null,
        "tooltip": null
    },
    {
        "row": [
            "ALL",
            "104年",
            "12月"
        ],
        "col": [
            "新北市"
        ],
        "colCode": null,
        "value": 212,
        "descriptionHtml": null,
        "qty": 0,
        "diff": null,
        "tooltip": null
    },
    {
        "row": [
            "ALL",
            "104年",
            "12月"
        ],
        "col": [
            "桃園市"
        ],
        "colCode": null,
        "value": 203,
        "descriptionHtml": null,
        "qty": 0,
        "diff": null,
        "tooltip": null
    },
    {
        "row": [
            "ALL",
            "104年",
            "12月"
        ],
        "col": [
            "新竹市"
        ],
        "colCode": null,
        "value": 41,
        "descriptionHtml": null,
        "qty": 0,
        "diff": null,
        "tooltip": null
    },
    {
        "row": [
            "ALL",
            "104年",
            "12月"
        ],
        "col": [
            "新竹縣"
        ],
        "colCode": null,
        "value": 89,
        "descriptionHtml": null,
        "qty": 0,
        "diff": null,
        "tooltip": null
    },
    {
        "row": [
            "ALL",
            "104年",
            "12月"
        ],
        "col": [
            "苗栗縣"
        ],
        "colCode": null,
        "value": 79,
        "descriptionHtml": null,
        "qty": 0,
        "diff": null,
        "tooltip": null
    },
    {
        "row": [
            "ALL",
            "104年",
            "12月"
        ],
        "col": [
            "臺中市"
        ],
        "colCode": null,
        "value": 275,
        "descriptionHtml": null,
        "qty": 0,
        "diff": null,
        "tooltip": null
    },
    {
        "row": [
            "ALL",
            "104年",
            "12月"
        ],
        "col": [
            "彰化縣"
        ],
        "colCode": null,
        "value": 206,
        "descriptionHtml": null,
        "qty": 0,
        "diff": null,
        "tooltip": null
    },
    {
        "row": [
            "ALL",
            "104年",
            "12月"
        ],
        "col": [
            "南投縣"
        ],
        "colCode": null,
        "value": 101,
        "descriptionHtml": null,
        "qty": 0,
        "diff": null,
        "tooltip": null
    },
    {
        "row": [
            "ALL",
            "104年",
            "12月"
        ],
        "col": [
            "雲林縣"
        ],
        "colCode": null,
        "value": 189,
        "descriptionHtml": null,
        "qty": 0,
        "diff": null,
        "tooltip": null
    },
    {
        "row": [
            "ALL",
            "104年",
            "12月"
        ],
        "col": [
            "嘉義市"
        ],
        "colCode": null,
        "value": 21,
        "descriptionHtml": null,
        "qty": 0,
        "diff": null,
        "tooltip": null
    },
    {
        "row": [
            "ALL",
            "104年",
            "12月"
        ],
        "col": [
            "嘉義縣"
        ],
        "colCode": null,
        "value": 118,
        "descriptionHtml": null,
        "qty": 0,
        "diff": null,
        "tooltip": null
    },
    {
        "row": [
            "ALL",
            "104年",
            "12月"
        ],
        "col": [
            "臺南市"
        ],
        "colCode": null,
        "value": 289,
        "descriptionHtml": null,
        "qty": 0,
        "diff": null,
        "tooltip": null
    },
    {
        "row": [
            "ALL",
            "104年",
            "12月"
        ],
        "col": [
            "高雄市"
        ],
        "colCode": null,
        "value": 364,
        "descriptionHtml": null,
        "qty": 0,
        "diff": null,
        "tooltip": null
    },
    {
        "row": [
            "ALL",
            "104年",
            "12月"
        ],
        "col": [
            "屏東縣"
        ],
        "colCode": null,
        "value": 229,
        "descriptionHtml": null,
        "qty": 0,
        "diff": null,
        "tooltip": null
    },
    {
        "row": [
            "ALL",
            "104年",
            "12月"
        ],
        "col": [
            "宜蘭縣"
        ],
        "colCode": null,
        "value": 83,
        "descriptionHtml": null,
        "qty": 0,
        "diff": null,
        "tooltip": null
    },
    {
        "row": [
            "ALL",
            "104年",
            "12月"
        ],
        "col": [
            "花蓮縣"
        ],
        "colCode": null,
        "value": 70,
        "descriptionHtml": null,
        "qty": 0,
        "diff": null,
        "tooltip": null
    },
    {
        "row": [
            "ALL",
            "104年",
            "12月"
        ],
        "col": [
            "臺東縣"
        ],
        "colCode": null,
        "value": 63,
        "descriptionHtml": null,
        "qty": 0,
        "diff": null,
        "tooltip": null
    },
    {
        "row": [
            "ALL",
            "104年",
            "12月"
        ],
        "col": [
            "澎湖縣"
        ],
        "colCode": null,
        "value": 13,
        "descriptionHtml": null,
        "qty": 0,
        "diff": null,
        "tooltip": null
    },
    {
        "row": [
            "ALL",
            "104年",
            "12月"
        ],
        "col": [
            "金門縣"
        ],
        "colCode": null,
        "value": 9,
        "descriptionHtml": null,
        "qty": 0,
        "diff": null,
        "tooltip": null
    },
    {
        "row": [
            "ALL",
            "104年",
            "12月"
        ],
        "col": [
            "連江縣"
        ],
        "colCode": null,
        "value": 0,
        "descriptionHtml": null,
        "qty": 0,
        "diff": null,
        "tooltip": null
    },
    {
        "row": [
            "ALL",
            "104年",
            "12月"
        ],
        "col": [
            "國道"
        ],
        "colCode": null,
        "value": 103,
        "descriptionHtml": null,
        "qty": 0,
        "diff": null,
        "tooltip": null
    },
    {
        "row": [
            "ALL",
            "104年",
            "12月"
        ],
        "col": [
            "其他"
        ],
        "colCode": null,
        "value": 17,
        "descriptionHtml": null,
        "qty": 0,
        "diff": null,
        "tooltip": null
    }
]