{"srs":"EPSG:4326","types":"all","results":[{"type":"roadcross","geometry":{"x":121.74635572839,"y":25.1296637382005},"town":"","county":"\u57FA\u9686\u5E02","name":"","NAME1":"\u4FE1\u4E00\u8DEF, ,\u7E23102, , ","NAME2":"\u7FA9\u4E09\u8DEF, , , , "},{"type":"roadcross","geometry":{"x":121.74635572839,"y":25.1296637382005},"town":"","county":"\u57FA\u9686\u5E02","name":"","NAME1":"\u4FE1\u4E00\u8DEF, ,\u7E23102, , ","NAME2":"\u7FA9\u4E09\u8DEF, , , , ,\u7F8E\u7334\u6A4B"},{"type":"roadcross","geometry":{"x":121.747483475256,"y":25.1298489646588},"town":"","county":"\u57FA\u9686\u5E02","name":"","NAME1":"\u4FE1\u4E00\u8DEF141\u5DF7,141\u5DF7, , , ","NAME2":"\u7FA9\u4E09\u8DEF12\u5DF7,12\u5DF7, , , "},{"type":"roadcross","geometry":{"x":121.747369101008,"y":25.1296668892418},"town":"","county":"\u57FA\u9686\u5E02","name":"","NAME1":"\u4FE1\u4E00\u8DEF141\u5DF7,141\u5DF7, , , ","NAME2":"\u7FA9\u4E09\u8DEF4\u5DF7,4\u5DF7, , , "}],"featureCount":4,"pages":1,"page":1,"status":"OK"}