{"srs":"EPSG:4326","types":"all","results":[{"type":"roadcross","geometry":{"x":121.070744516394,"y":24.8278056701164},"town":"","county":"\u65B0\u7AF9\u7E23","name":"","NAME1":"\u4E2D\u6B63\u8DEF, , , , ","NAME2":"\u548C\u5E73\u8857, , , , "},{"type":"roadcross","geometry":{"x":121.080219118211,"y":24.8276705899085},"town":"","county":"\u65B0\u7AF9\u7E23","name":"","NAME1":"\u4E2D\u6B63\u8DEF, , , , ","NAME2":"\u548C\u5E73\u8857, , , , "},{"type":"roadcross","geometry":{"x":121.180609087443,"y":24.7070536602411},"town":"","county":"\u65B0\u7AF9\u7E23","name":"","NAME1":"\u4E2D\u6B63\u8DEF, , , , ","NAME2":"\u548C\u5E73\u8857, , , , "},{"type":"roadcross","geometry":{"x":121.079416397187,"y":24.8273102043198},"town":"","county":"\u65B0\u7AF9\u7E23","name":"","NAME1":"\u4E2D\u6B63\u8DEF281\u5DF7,281\u5DF7, , , ","NAME2":"\u548C\u5E73\u8857, , , , "},{"type":"roadcross","geometry":{"x":121.077658972545,"y":24.8270579565281},"town":"","county":"\u65B0\u7AF9\u7E23","name":"","NAME1":"\u4E2D\u6B63\u8DEF311\u5DF7,311\u5DF7, , , ","NAME2":"\u548C\u5E73\u8857, , , , "},{"type":"roadcross","geometry":{"x":121.073037420664,"y":24.8270473616734},"town":"","county":"\u65B0\u7AF9\u7E23","name":"","NAME1":"\u4E2D\u6B63\u8DEF517\u5DF7,517\u5DF7, , , ","NAME2":"\u548C\u5E73\u8857, , , , "}],"featureCount":6,"pages":1,"page":1,"status":"OK"}