{"srs":"EPSG:4326","types":"all","results":[{"type":"roadcross","geometry":{"x":121.526746290445,"y":25.1439768594879},"town":"","county":"\u81FA\u5317\u5E02","name":"","NAME1":"\u884C\u7FA9\u8DEF, , , , ","NAME2":"\u6CC9\u6E90\u8DEF, , , , "},{"type":"roadcross","geometry":{"x":121.526746290445,"y":25.1439768594879},"town":"","county":"\u81FA\u5317\u5E02","name":"","NAME1":"\u884C\u7FA9\u8DEF, , , , ","NAME2":"\u6CC9\u6E90\u8DEF,\u967D\u6295\u516C\u8DEF, , , "}],"featureCount":2,"pages":1,"page":1,"status":"OK"}